tanjun/__init__.py
tanjun/abc.py
tanjun/annotations.py
tanjun/checks.py
tanjun/clients.py
tanjun/components.py
tanjun/conversion.py
tanjun/errors.py
tanjun/hooks.py
tanjun/injecting.py
tanjun/parsing.py
tanjun/permissions.py
tanjun/py.typed
tanjun/schedules.py
tanjun/utilities.py
tanjun/_internal/__init__.py
tanjun/_internal/cache.py
tanjun/_internal/localisation.py
tanjun/commands/__init__.py
tanjun/commands/base.py
tanjun/commands/menu.py
tanjun/commands/message.py
tanjun/commands/slash.py
tanjun/context/__init__.py
tanjun/context/autocomplete.py
tanjun/context/base.py
tanjun/context/menu.py
tanjun/context/message.py
tanjun/context/slash.py
tanjun/dependencies/__init__.py
tanjun/dependencies/async_cache.py
tanjun/dependencies/callbacks.py
tanjun/dependencies/data.py
tanjun/dependencies/limiters.py
tanjun/dependencies/locales.py
tanjun/dependencies/owners.py
tanjun/dependencies/reloaders.py
hikari_tanjun-2.17.7.dist-info/LICENSE
hikari_tanjun-2.17.7.dist-info/WHEEL
hikari_tanjun-2.17.7.dist-info/METADATA
hikari_tanjun-2.17.7.dist-info/RECORD
