Metadata-Version: 2.3
Name: hikari-tanjun
Version: 2.17.7
Summary: A flexible command framework designed to extend Hikari.
Keywords: hikari
Author-email: Faster Speeding <lucina@lmbyrne.dev>
Requires-Python: >=3.11.0,<3.14
Classifier: Development Status :: 5 - Production/Stable
Classifier: License :: OSI Approved :: BSD License
Classifier: Intended Audience :: Developers
Classifier: Natural Language :: English
Classifier: Operating System :: OS Independent
Classifier: Programming Language :: Python :: 3.11
Classifier: Programming Language :: Python :: 3.12
Classifier: Programming Language :: Python :: 3.13
Classifier: Programming Language :: Python :: Implementation :: CPython
Classifier: Topic :: Communications :: Chat
Classifier: Topic :: Software Development :: Libraries
Classifier: Topic :: Software Development :: Libraries :: Python Modules
Classifier: Topic :: Utilities
Classifier: Typing :: Typed
Requires-Dist: alluka>=0.2.0, <1
Requires-Dist: hikari>=2.0.0.dev115, <3
Requires-Dist: typing-extensions>=4.5, <5
Project-URL: Changelog, https://tanjun.cursed.solutions/changelog
Project-URL: Documentation, https://tanjun.cursed.solutions/
Project-URL: Homepage, https://github.com/FasterSpeeding/Tanjun
Project-URL: Repository, https://github.com/FasterSpeeding/Tanjun
